gap_study_utils/__init__.py
gap_study_utils/_version.py
gap_study_utils/analysis_data.py
gap_study_utils/constants.py
gap_study_utils/gap_funcs.py
gap_study_utils/gap_window.py
gap_study_utils/logger.py
gap_study_utils/mcmc_runner.py
gap_study_utils/noise_curves.py
gap_study_utils/plotting.py
gap_study_utils/pygtc.py
gap_study_utils/random.py
gap_study_utils/signal_utils.py
gap_study_utils/utils.py
gap_study_utils/sampling/__init__.py
gap_study_utils/sampling/likelihood.py
pywavelet.case_studies.gaps-0.1.4.dist-info/METADATA
pywavelet.case_studies.gaps-0.1.4.dist-info/WHEEL
pywavelet.case_studies.gaps-0.1.4.dist-info/top_level.txt
pywavelet.case_studies.gaps-0.1.4.dist-info/RECORD
